{"razaoSocial": "VALOR CONTABIL ASSESSORIA E CONSULTORIA LTDA", "cnpj": "42.555.007/0001-10", "modeloDeContrato": "Sittax - Simples Nacional", "consultor": "William Dalmagro", "emails": [" FELIPE@VALORCONTABILRS.COM.BR", " FELIPE@VALORCONTABILRS.COM.BR", " FELIPE@VALORCONTABILRS.COM.BR"], "phones": ["+5551992558953", "+5551992558953"], "valorMensalidade": "R$ 675,00 (seiscentos e setenta e cinco reais)", "valorLicenca": "R$ 1.805,00 (um mil oitocentos e cinco reais)", "qtdCnpj": "100", "diretor": "Felipe dos Santos Bianchi"}