{"razaoSocial": "TASSO CONTABILIDADE LTDA", "cnpj": "12.255.804/0001-10", "modeloDeContrato": "Sittax - Simples Nacional", "consultor": "Victor Augusto Menezes", "emails": [" GUILHERME@TASSOCONTABILDADE.COM.BR", " GUILHERME@TASSOCONTABILDADE.COM.BR", " GUILHERME@TASSOCONTABILDADE.COM.BR"], "phones": ["+554832404500", "+554832404500"], "valorMensalidade": "R$ 950,00 (novecentos e cinquenta reais)", "valorLicenca": "R$ 2.200,00 (dois mil e duzentos reais)", "qtdCnpj": "200", "diretor": "GUILHERME TASSO"}